XinyidaiBaoleiJiJiansheZhinan10202105/README.md
XinyidaiBaoleiJiJiansheZhinan10202105/__init__.py
XinyidaiBaoleiJiJiansheZhinan10202105/__main__.py
XinyidaiBaoleiJiJiansheZhinan10202105/file.pdf
XinyidaiBaoleiJiJiansheZhinan10202105/index.html
xinyidai_baolei_ji_jianshe_zhinan_1_0_202105-2024.3.6.0.dist-info/METADATA
xinyidai_baolei_ji_jianshe_zhinan_1_0_202105-2024.3.6.0.dist-info/WHEEL
xinyidai_baolei_ji_jianshe_zhinan_1_0_202105-2024.3.6.0.dist-info/entry_points.txt
xinyidai_baolei_ji_jianshe_zhinan_1_0_202105-2024.3.6.0.dist-info/top_level.txt
xinyidai_baolei_ji_jianshe_zhinan_1_0_202105-2024.3.6.0.dist-info/RECORD
